onecharts/__init__.py
onecharts/__version__.py
OneCharts-0.1.2.dist-info/LICENSE
OneCharts-0.1.2.dist-info/METADATA
OneCharts-0.1.2.dist-info/WHEEL
OneCharts-0.1.2.dist-info/top_level.txt
OneCharts-0.1.2.dist-info/RECORD
