Metadata-Version: 2.1
Name: OneCharts
Version: 0.1.2
Summary: Create and Manage Charts with Ease
Home-page: https://github.com/onechartsio/onecharts-py
License: Apache License 2.0
Platform: UNKNOWN
Classifier: License :: OSI Approved :: Apache Software License
Classifier: Programming Language :: Python :: 3.5
Classifier: Programming Language :: Python :: 3.6
Classifier: Programming Language :: Python :: 3.7
Classifier: Programming Language :: Python :: 3.8
Classifier: Programming Language :: Python :: 3.9
License-File: LICENSE
Requires-Dist: requests >=2.31
Requires-Dist: ipython ==7.34.0
